<?xml version="1.0"?>
<Devices>

    <Device type="custom" id="slider_device">
        <Name>Slider Device</Name>

        <ConfigUI>
            <Field id="settingsLabel" type="label">
                <Label>Placeholder</Label>
            </Field>
        </ConfigUI>

        <States>
            <State id="slider_value">
                <ValueType>Integer</ValueType>
                <TriggerLabel>Slider Value</TriggerLabel>
                <ControlPageLabel>Slider Value</ControlPageLabel>
            </State>
        </States>

        <UiDisplayStateId>slider_value</UiDisplayStateId>
    </Device>

</Devices>
